odoo/addons/ssi_master_data_mixin/README.rst
odoo/addons/ssi_master_data_mixin/__init__.py
odoo/addons/ssi_master_data_mixin/__manifest__.py
odoo/addons/ssi_master_data_mixin/i18n/ssi_master_data_mixin.pot
odoo/addons/ssi_master_data_mixin/models/__init__.py
odoo/addons/ssi_master_data_mixin/models/mixin_master_data.py
odoo/addons/ssi_master_data_mixin/static/description/icon.png
odoo/addons/ssi_master_data_mixin/static/description/index.html
odoo/addons/ssi_master_data_mixin/static/img/bug.png
odoo/addons/ssi_master_data_mixin/static/img/circuit.png
odoo/addons/ssi_master_data_mixin/static/img/download.png
odoo/addons/ssi_master_data_mixin/static/img/info.png
odoo/addons/ssi_master_data_mixin/static/img/medal.png
odoo/addons/ssi_master_data_mixin/static/img/questions.png
odoo/addons/ssi_master_data_mixin/static/img/workflow.png
odoo/addons/ssi_master_data_mixin/tests/__init__.py
odoo/addons/ssi_master_data_mixin/tests/base.py
odoo/addons/ssi_master_data_mixin/tests/dummy_model.py
odoo/addons/ssi_master_data_mixin/tests/scenario_create_data.yml
odoo/addons/ssi_master_data_mixin/tests/scenario_create_invalid_data.yml
odoo/addons/ssi_master_data_mixin/tests/scenario_duplicate_code.yml
odoo/addons/ssi_master_data_mixin/tests/scenario_generate_code.yml
odoo/addons/ssi_master_data_mixin/tests/test_create_data.py
odoo/addons/ssi_master_data_mixin/tests/test_duplicate_code.py
odoo/addons/ssi_master_data_mixin/tests/test_generate_code.py
odoo/addons/ssi_master_data_mixin/views/mixin_master_data_views.xml
odoo_addon_ssi_master_data_mixin-18.0.1.1.0.dist-info/METADATA
odoo_addon_ssi_master_data_mixin-18.0.1.1.0.dist-info/WHEEL
odoo_addon_ssi_master_data_mixin-18.0.1.1.0.dist-info/top_level.txt
odoo_addon_ssi_master_data_mixin-18.0.1.1.0.dist-info/RECORD
