Metadata-Version: 2.1
Name: odoo-addon-ssi_master_data_mixin
Version: 18.0.1.1.0
Requires-Python: >=3.10
Requires-Dist: odoo-addon-ssi_print_mixin==18.0.*
Requires-Dist: odoo-addon-ssi_sequence_mixin==18.0.*
Requires-Dist: odoo==18.0.*
Summary: Master Data Mixin
Home-page: https://github.com/open-synergy/ssi-mixin
License: AGPL-3
Author: PT. Simetri Sinergi Indonesia
Classifier: Programming Language :: Python
Classifier: Framework :: Odoo
Classifier: Framework :: Odoo :: 18.0
Classifier: License :: OSI Approved :: GNU Affero General Public License v3
